nya/__init__.py
nya/_version.py
nya/py.typed
nya/crossimpl/__init__.py
nya/crossimpl/settings.py
nya/hikari/__init__.py
nya/miru/__init__.py
nya/utils/__init__.py
nya/utils/url.py
hikari_nya-0.1.2.dist-info/METADATA
hikari_nya-0.1.2.dist-info/WHEEL
hikari_nya-0.1.2.dist-info/RECORD
