Metadata-Version: 2.4
Name: hikari-nya
Version: 0.1.2
Summary: Sometimes useful set of tools for hikari-based discord bot projects
Author: anamoyee
Requires-Python: >=3.12
Requires-Dist: hikari>=2.3.2
Provides-Extra: arc
Requires-Dist: hikari-arc<3,>=2.1.0; extra == 'arc'
Provides-Extra: miru
Requires-Dist: hikari-miru<5,>=4.2.0; extra == 'miru'
